pretix_fzbackend_utils/__init__.py
pretix_fzbackend_utils/apps.py
pretix_fzbackend_utils/general_views.py
pretix_fzbackend_utils/payment.py
pretix_fzbackend_utils/signals.py
pretix_fzbackend_utils/urls.py
pretix_fzbackend_utils/utils.py
pretix_fzbackend_utils/fz_utilites/__init__.py
pretix_fzbackend_utils/fz_utilites/fzException.py
pretix_fzbackend_utils/fz_utilites/fzOrderChangeManager.py
pretix_fzbackend_utils/locale/django.pot
pretix_fzbackend_utils/locale/de/LC_MESSAGES/django.mo
pretix_fzbackend_utils/locale/de/LC_MESSAGES/django.po
pretix_fzbackend_utils/locale/de_Informal/.gitkeep
pretix_fzbackend_utils/locale/de_Informal/LC_MESSAGES/django.mo
pretix_fzbackend_utils/locale/de_Informal/LC_MESSAGES/django.po
pretix_fzbackend_utils/static/pretix_fzbackend_utils/.gitkeep
pretix_fzbackend_utils/static/pretix_fzbackend_utils/only_one_item.js
pretix_fzbackend_utils/templates/pretix_fzbackend_utils/control.html
pretix_fzbackend_utils/templates/pretix_fzbackend_utils/settings.html
pretix_fzbackend_utils/views/__init__.py
pretix_fzbackend_utils/views/convert_ticket_only.py
pretix_fzbackend_utils/views/exchange_rooms.py
pretix_fzbackend_utils/views/transfer_order.py
pretix_fzbackend_utils-1.3.20260108.3.dist-info/licenses/LICENSE
pretix_fzbackend_utils-1.3.20260108.3.dist-info/METADATA
pretix_fzbackend_utils-1.3.20260108.3.dist-info/WHEEL
pretix_fzbackend_utils-1.3.20260108.3.dist-info/entry_points.txt
pretix_fzbackend_utils-1.3.20260108.3.dist-info/top_level.txt
pretix_fzbackend_utils-1.3.20260108.3.dist-info/RECORD
