Metadata-Version: 2.4
Name: pretix-fzbackend-utils
Version: 1.3.20260108.3
Summary: Pretix utils plugin to work together with fz-backend
Author-email: Furizon Team <webservice@furizon.net>
Maintainer-email: Furizon Team <webservice@furizon.net>
License: Apache
Project-URL: homepage, https://github.com/APSfurizon/pretix-fzbackend-utils
Project-URL: repository, https://github.com/APSfurizon/pretix-fzbackend-utils
Keywords: pretix
License-File: LICENSE
Dynamic: license-file
